[
  {
    "category_id": "1096",
    "category_name": "Series: Ramadan 2026 (AR)",
    "parent_id": 0
  },
  {
    "category_id": "1052",
    "category_name": "Series: Nordic 4K",
    "parent_id": 0
  },
  {
    "category_id": "1079",
    "category_name": "Series: Julkalender (SE)",
    "parent_id": 0
  },
  {
    "category_id": "975",
    "category_name": "Series: Nordic HBO",
    "parent_id": 0
  },
  {
    "category_id": "976",
    "category_name": "Series: Nordic Netflix",
    "parent_id": 0
  },
  {
    "category_id": "978",
    "category_name": "Series: Nordic Viaplay",
    "parent_id": 0
  },
  {
    "category_id": "977",
    "category_name": "Series: Nordic Prime Video",
    "parent_id": 0
  },
  {
    "category_id": "991",
    "category_name": "Series: Nordic Apple TV",
    "parent_id": 0
  },
  {
    "category_id": "979",
    "category_name": "Series: Nordic Disney",
    "parent_id": 0
  },
  {
    "category_id": "567",
    "category_name": "Series: HBO ",
    "parent_id": 0
  },
  {
    "category_id": "568",
    "category_name": "Series: Netflix",
    "parent_id": 0
  },
  {
    "category_id": "588",
    "category_name": "Series: Apple TV+",
    "parent_id": 0
  },
  {
    "category_id": "572",
    "category_name": "Series: Other",
    "parent_id": 0
  },
  {
    "category_id": "584",
    "category_name": "Series: Arabic",
    "parent_id": 0
  },
  {
    "category_id": "576",
    "category_name": "Series: Danish",
    "parent_id": 0
  },
  {
    "category_id": "1024",
    "category_name": "Series: Finland",
    "parent_id": 0
  },
  {
    "category_id": "580",
    "category_name": "Series: Ex-Yu",
    "parent_id": 0
  },
  {
    "category_id": "575",
    "category_name": "Series: Français",
    "parent_id": 0
  },
  {
    "category_id": "1015",
    "category_name": "Series: Norwegian",
    "parent_id": 0
  },
  {
    "category_id": "570",
    "category_name": "Series: Netherlands",
    "parent_id": 0
  },
  {
    "category_id": "596",
    "category_name": "Series: Nordic Kids (Multi-Audio)",
    "parent_id": 0
  },
  {
    "category_id": "1099",
    "category_name": "Series: Germany",
    "parent_id": 0
  },
  {
    "category_id": "573",
    "category_name": "Series:  Polish",
    "parent_id": 0
  },
  {
    "category_id": "590",
    "category_name": "Series: Spanish",
    "parent_id": 0
  },
  {
    "category_id": "566",
    "category_name": "Series: Swedish",
    "parent_id": 0
  },
  {
    "category_id": "618",
    "category_name": "Series: Norway",
    "parent_id": 0
  },
  {
    "category_id": "583",
    "category_name": "Series: Português",
    "parent_id": 0
  },
  {
    "category_id": "571",
    "category_name": "Series: Turkish",
    "parent_id": 0
  }
]